pynamite/__init__.py
pynamite/example.py
pynamite-0.0.1.dist-info/LICENSE
pynamite-0.0.1.dist-info/METADATA
pynamite-0.0.1.dist-info/WHEEL
pynamite-0.0.1.dist-info/top_level.txt
pynamite-0.0.1.dist-info/RECORD
