Metadata-Version: 2.1
Name: pynamite
Version: 0.0.1
Summary: DynomoDB wrapper - makes AWS dynamoDB simple to use
Home-page: https://github.com/xzava/pynamite
Author: Mike Hall
Author-email: micheal.hall+pynamite@gmail.com
License: UNKNOWN
Project-URL: Bug Tracker, https://github.com/xzava/pynamite/issues
Platform: UNKNOWN
Classifier: Programming Language :: Python :: 3
Classifier: License :: OSI Approved :: MIT License
Classifier: Operating System :: OS Independent
Requires-Python: >=3.6
License-File: LICENSE
